Workbook

Sheet Overview
B2: ByteHub — Master Merged Catalog & Procurement Review
B3: Consolidated from: Anker/Soundcore/eufy Price List (17-Mar-2026) · Joyroom Price List (26-Jul-2026) · ByteHub Procurement Plan · catalog_readiness.xlsx · Product_Catalog (1) & (2)
B5: ⚠ HEADLINE FINDING — the procurement plan's own budget math does not add up
B6: • | C6: Re-multiplying the plan's own quantities × its own RDP (cost) figures gives a Must-Buy basket of ≈ 78,475 ج.م and a Test-Buy basket of ≈ 37,310 ج.م — a combined ≈ 115,785 ج.م, not the ≈ 38,500 ج.م stated in section 3 of the plan (roughly 3x understated). See the 'Investment Summary' sheet — every total there is a live formula (qty × verified RDP), so it will recalculate correctly if quantities change.
B8: • | C8: Three RDP (wholesale cost) figures quoted in the plan do not match the supplier price lists it says it was built from. The worst case (Anker A2667, 65W GaN charger) turns a claimed 50% margin into a real 16.5% margin — below the plan's own 'Avoid' threshold (<20%) — and its assumed market retail range (1,000–1,400 ج.م) is actually BELOW the real wholesale cost (1,665 ج.م), which would mean a loss on every unit sold at that range. Full detail in 'Pricing Corrections'.
B10: • | C10: One Joyroom product code is wrong: the plan's 'JR-PK1' retractable-cable power bank does not exist in the Joyroom list — its price figures (990/1,399) match model JR-PR1 instead. Confirm the SKU with Joyroom before ordering.
B12: • | C12: This workbook does not change the plan's purchasing judgement calls (Must/Test/Avoid logic) — it re-verifies every number against the two source price lists, fixes the arithmetic, and flags what needs a human decision.
B15: What's in this workbook
B16: Sheet | C16: What it contains
B17: Must Buy | C17: 9 SKUs — corrected RDP/RRP, live margin & cost formulas, qty, notes.
B18: Test Buy | C18: 9 SKUs — same treatment, incl. the JR-PK1→JR-PR1 correction.
B19: Avoid | C19: 5 SKUs — verified, incl. the Anker A1336 RDP correction (margin is actually ~18%, not 28%).
B20: Investment Summary | C20: Live totals by list and by supplier — replaces the plan's static, incorrect numbers.
B21: Pricing Corrections | C21: Every discrepancy found between the plan and the two source price lists, with the source line quoted.
B22: Additional Opportunities | C22: Anker/Joyroom/eufy/Soundcore SKUs already priced in the two supplier lists but not mentioned anywhere in the plan — candidates for a v2 basket.
B23: Website Readiness | C23: The 7 draft products / 22 build-blockers from catalog_readiness.xlsx, with a recommended real SKU (and its RDP/RRP) to close each price gap where one exists.
B24: Generic Catalog (USD) | C24: Product_Catalog (1) & (2) merged — flagged as NOT sourced from the current Anker/Joyroom supplier lists; recommendation included.
B25: Negotiation & KPIs | C25: Condensed supplier-negotiation talking points and success KPIs from the plan, unchanged.

Sheet Must Buy
A1: ByteHub Procurement — Must Buy
A2: # | B2: Product | C2: Category | D2: Supplier | E2: Model / SKU | F2: RDP (plan, EGP) | G2: RDP (verified, EGP) | H2: RRP (verified, EGP) | I2: Local Market (EGP) | J2: Margin % (RRP basis) | K2: Qty | L2: Est. Cost (EGP, formula) | M2: Verification Notes
A3: 1 | B3: Joyroom JR-TCG13 GaN 45W charger | C3: شواحن | D3: Joyroom | E3: JR-TCG13 | F3: 440 | G3: 440 | H3: 750 | I3: 550-720 | J3: =IFERROR((H3-G3)/H3,"") -> 0.41333333 | K3: 30 | L3: =IFERROR(K3*G3,"see notes") -> 13200 | M3: Matches Joyroom list exactly.
A4: 2 | B4: Joyroom JR-TCF20 PD 20W Charger | C4: شواحن | D4: Joyroom | E4: JR-TCF20 | F4: 290 | G4: 290 | H4: 550 | I4: 350-500 | J4: =IFERROR((H4-G4)/H4,"") -> 0.47272727 | K4: 25 | L4: =IFERROR(K4*G4,"see notes") -> 7250 | M4: Matches Joyroom list exactly.
A5: 3 | B5: The Joyroom S-A59 (Vibrant Series) 1.2 -meter Type-C to Type-C conversion | C5: كابلات | D5: Joyroom | E5: S-A59 | F5: 120 | G5: 120 | H5: 325 | I5: 200-300 | J5: =IFERROR((H5-G5)/H5,"") -> 0.63076923 | K5: 50 | L5: =IFERROR(K5*G5,"see notes") -> 6000 | M5: Matches Joyroom list exactly (multi-colour SKU, same price).
A6: 4 | B6: Joyroom S-A42 Usb-A To Type-C 1.2m Cable Crystal-Clear 3A | C6: كابلات | D6: Joyroom | E6: S-A42 | F6: 165 | G6: 165 | H6: 375 | I6: 250-350 | J6: =IFERROR((H6-G6)/H6,"") -> 0.56 | K6: 30 | L6: =IFERROR(K6*G6,"see notes") -> 4950 | M6: Matches Joyroom list (USB-A variant; Type-C-Type-C 60W variant is RDP 180/RRP 390).
A7: 5 | B7: Joyroom JR-PBF12 10000mAh LED Power Bank 22.5W | C7: باور بانك | D7: Joyroom | E7: JR-PBF12 | F7: 420 | G7: 420 | H7: 730 | I7: 580-730 | J7: =IFERROR((H7-G7)/H7,"") -> 0.42465753 | K7: 20 | L7: =IFERROR(K7*G7,"see notes") -> 8400 | M7: Matches Joyroom list exactly.
A8: 6 | B8: JR-QP192 Star Series Mini Power Bank 20000mAh, 22.5W Max Super Fast Charging, Digital Display, Compact & Lightweight, Dual USB-C In/Out + USB-A - Black | C8: باور بانك | D8: Joyroom | E8: JR-QP192 Mini | F8: 925 | G8: 925 | H8: 1350 | I8: 1,100-1,400 | J8: =IFERROR((H8-G8)/H8,"") -> 0.31481481 | K8: 15 | L8: =IFERROR(K8*G8,"see notes") -> 13875 | M8: Matches Joyroom list exactly.
A9: 7 | B9: The Joyroom JR-T03S Standard Edition | C9: سماعات | D9: Joyroom | E9: JR-T03S | F9: 600 | G9: 600 | H9: 999 | I9: 700-850 | J9: =IFERROR((H9-G9)/H9,"") -> 0.3993994 | K9: 20 | L9: =IFERROR(K9*G9,"see notes") -> 12000 | M9: Matches Joyroom list exactly.
A10: 8 | B10: Anker A2149 PowerPort III 20W Cube PD USB-C Wall Charger | C10: شواحن | D10: Anker | E10: A2149 | F10: 360 | G10: 360 | H10: 475 | I10: 395-450 | J10: =IFERROR((H10-G10)/H10,"") -> 0.24210526 | K10: 20 | L10: =IFERROR(K10*G10,"see notes") -> 7200 | M10: Matches Anker list exactly.
A11: 9 | B11: Anker PowerLine A8852 III USB-C to USB-C cable | C11: كابلات | D11: Anker | E11: A8852 | F11: 280 | G11: 460 | H11: 577 | I11: 300-400 (plan's guess — unverified) | J11: =IFERROR((H11-G11)/H11,"") -> 0.20277296 | K11: 20 | L11: =IFERROR(K11*G11,"see notes") -> 9200 | M11: MISMATCH: plan's RDP 280 does not appear in the Anker list for A8852; the sheet shows RDP 460 / RRP 577 twice. Real margin is only 20.3%, below this plan's own 35% Must-Buy bar, and the plan's assumed market price (300-400) is BELOW the real cost. Recommend re-costing before ordering — move to 'Test Buy' or drop until a real EG street price is checked.
K12: TOTAL | L12: =SUM(L3:L11) -> 82075

Sheet Test Buy
A1: ByteHub Procurement — Test Buy
A2: # | B2: Product | C2: Category | D2: Supplier | E2: Model / SKU | F2: RDP (plan, EGP) | G2: RDP (verified, EGP) | H2: RRP (verified, EGP) | I2: Local Market (EGP) | J2: Margin % (RRP basis) | K2: Qty | L2: Est. Cost (EGP, formula) | M2: Verification Notes
A3: 1 | B3: Joyroom SA21-1T3 cable Speedy Series 100W 3-in 1 Fast Charging Cable (USB-A to L+C+M) | C3: كابلات | D3: Joyroom | E3: SA21-1T3 | F3: 265 | G3: 265 | H3: 525 | I3: 400-500 | J3: =IFERROR((H3-G3)/H3,"") -> 0.4952381 | K3: 10 | L3: =IFERROR(K3*G3,"see notes") -> 2650 | M3: Joyroom uses SA21-1T3 for TWO cables at different prices (Type-C-input 30W: RDP 275/RRP 550, and USB-A-input 100W: RDP 265/RRP 525). Plan's numbers match the 100W/USB-A version — confirm that is the one intended before ordering.
A4: 2 | B4: Joyroom SA21-2T3 cable Speedy Series 100W 6-in 1 Fast Charging Cable (USB-A+Type C to L+C+M C to L+C+M) | C4: كابلات | D4: Joyroom | E4: SA21-2T3 | F4: 495 | G4: 495 | H4: 790 | I4: 600-700 | J4: =IFERROR((H4-G4)/H4,"") -> 0.37341772 | K4: 8 | L4: =IFERROR(K4*G4,"see notes") -> 3960 | M4: Matches Joyroom list exactly.
A5: 3 | B5: Joyroom JR-PR1 10000mAh Mini Power Bank - 22.5W | C5: باور بانك | D5: Joyroom | E5: JR-PK1 → JR-PR1 | F5: 990 | G5: 990 | H5: 1399 | I5: 1,100-1,300 | J5: =IFERROR((H5-G5)/H5,"") -> 0.29235168 | K5: 5 | L5: =IFERROR(K5*G5,"see notes") -> 4950 | M5: SKU CORRECTION: 'JR-PK1' does not exist in the Joyroom list. The quoted price (990/1,399) matches model JR-PR1 (22.5W built-in retractable-cable power bank, 10,000mAh) exactly — use JR-PR1 when ordering.
A6: 4 | B6: JOYROOM JR-PBM01 20W Magnetic Wireless Power Bank 10000mAh with Built-in Cable & Kickstand | C6: باور بانك | D6: Joyroom | E6: JR-PBM01 | F6: 1100 | G6: 1100 | H6: 1500 | I6: 1,200-1,400 | J6: =IFERROR((H6-G6)/H6,"") -> 0.26666667 | K6: 5 | L6: =IFERROR(K6*G6,"see notes") -> 5500 | M6: Matches Joyroom list exactly.
A7: 5 | B7: Joyroom JR-FN3 ANC+ENC True Wireless Bluetooth Earphones Funpods series | C7: سماعات | D7: Joyroom | E7: JR-FN3 | F7: 925 | G7: 925 | H7: 1400 | I7: 1,200-1,500 | J7: =IFERROR((H7-G7)/H7,"") -> 0.33928571 | K7: 8 | L7: =IFERROR(K7*G7,"see notes") -> 7400 | M7: Matches Joyroom list exactly.
A8: 6 | B8: Anker 735 Nano II 65W GaN 3-Port Wall Charger for MacBook | C8: شواحن | D8: Anker | E8: A2667 | F8: 830 | G8: 1665 | H8: 1995 | I8: 1,000-1,400 (plan's guess — below real cost) | J8: =IFERROR((H8-G8)/H8,"") -> 0.16541353 | K8: 5 | L8: =IFERROR(K8*G8,"see notes") -> 8325 | M8: CRITICAL MISMATCH: the Anker list shows A2667G12 (735 PowerPort III, 3-Port 65W POD) at RDP 1,665 / RRP 1,995 — not RDP 830/RRP 1,665 as in the plan. Real margin is only 16.5%, below this plan's own 20% Avoid threshold, and the plan's assumed market range (1,000-1,400) is BELOW the real wholesale cost, which would be a guaranteed loss at that price. Recommend moving this SKU to Avoid until a real local sell-through price above 1,665 EGP is confirmed.
A9: 7 | B9: Joyroom S-A60 StarTalk 100W USB-C Data and Charging Cable 1.2m | C9: كابلات | D9: Joyroom | E9: S-A60 | F9: 185 | G9: 185 | H9: 450 | I9: 300-400 | J9: =IFERROR((H9-G9)/H9,"") -> 0.58888889 | K9: 15 | L9: =IFERROR(K9*G9,"see notes") -> 2775 | M9: Matches Joyroom list exactly.
K10: TOTAL | L10: =SUM(L3:L9) -> 35560

Sheet Avoid
A1: ByteHub Procurement — Avoid
A2: # | B2: Product | C2: Category | D2: Supplier | E2: Model / SKU | F2: RDP (plan, EGP) | G2: RDP (verified, EGP) | H2: RRP (verified, EGP) | I2: Local Market (EGP) | J2: Margin % (RRP basis) | K2: Qty | L2: Est. Cost (EGP, formula) | M2: Verification Notes
A3: 1 | B3: كابل PowerLine+ C-L 6ft | C3: كابلات | D3: Anker | E3: A8843 | F3: 2199 | G3: 2199 | H3: 2999 | I3: n/a — priced above market | J3: =IFERROR((H3-G3)/H3,"") -> 0.26675559 | K3: 0 | L3: — | M3: Matches Anker list exactly. Confirmed: RDP is far above realistic EG retail; Joyroom S-A43 (Crystal-Clear C:L, RDP 185) is the recommended substitute, as the plan already suggests.
A4: 2 | B4: باور بانك Zolo 10K | C4: باور بانك | D4: Anker | E4: A110D | F4: 1150 | G4: 1150 | H4: 1399 | I4: n/a — weak discount | J4: =IFERROR((H4-G4)/H4,"") -> 0.17798427 | K4: 0 | L4: — | M4: Matches Anker list exactly.
A5: 3 | B5: باور بانك Prime 20K 200W | C5: باور بانك | D5: Anker | E5: A1336 | F5: 5450 | G5: 8100 | H5: 9898 | I5: n/a — niche/high-ticket | J5: =IFERROR((H5-G5)/H5,"") -> 0.18165286 | K5: 0 | L5: — | M5: MISMATCH: plan's RDP 5,450 belongs to a different Anker product line (several MagGo wireless charging docks share that exact RDP). The real A1336 (Prime Power Bank 20K/200W) RDP is 8,100 / RRP 9,898. Real margin is ~18%, close to — not above — the plan's own 20% Avoid cut-off, so the 'avoid unless a customer requests it' call is still correct, just for a lower margin than stated.
A6: 4 | B6: سماعات T03S PRO MAX | C6: سماعات | D6: Joyroom | E6: JR-T03S PRO MAX | F6: 750 | G6: 750 | H6: 1050 | I6: n/a — thin margin vs base model | J6: =IFERROR((H6-G6)/H6,"") -> 0.28571429 | K6: 0 | L6: — | M6: Matches Joyroom list exactly.
A7: 5 | B7: باور بانك 30K | C7: باور بانك | D7: Joyroom | E7: JR-QP193 | F7: 1175 | G7: 1175 | H7: 1490 | I7: n/a — heavy/thin margin | J7: =IFERROR((H7-G7)/H7,"") -> 0.2114094 | K7: 0 | L7: — | M7: Matches Joyroom list exactly.
K8: TOTAL | L8: Not purchased

Sheet Investment Summary
A1: Investment Summary — live formulas, corrected pricing
A3: Basket | B3: # of SKUs | C3: Total Cost (EGP) | D3: Source
A4: Must Buy | B4: =COUNTA('Must Buy'!B3:B11) -> 9 | C4: ='Must Buy'!L12 -> 82075 | D4: Must Buy sheet, verified RDP
A5: Test Buy | B5: =COUNTA('Test Buy'!B3:B9) -> 7 | C5: ='Test Buy'!L10 -> 35560 | D5: Test Buy sheet, verified RDP
A6: TOTAL (verified) | B6: =B4+B5 -> 16 | C6: =C4+C5 -> 117635 | D6: Sum of the two baskets above
A8: For comparison — the plan's own stated total (section 3)
A9: Plan's stated total | B9: 18 | C9: 38500 | D9: ByteHub Procurement Plan, section 3 — does not reconcile with its own qty × RDP
A11: Gap explained
A12: The plan's Must-Buy total (~28,000 ج.م) and Test-Buy total (~10,500 ج.م) do not equal its own quantity × RDP figures — re-multiplying its own table gives ~78,475 and ~37,310 ج.م respectively (~115,785 ج.م combined), before any of the pricing corrections on the 'Pricing Corrections' sheet are applied. With those corrections included, the true verified total is the figure in the TOTAL row above. Recommend re-approving the budget against this sheet, not section 3 of the original plan.
A14: Supplier split (Must Buy + Test Buy, verified)
A15: Supplier | B15: Cost (EGP) | C15: % of total
A16: Joyroom | B16: =SUMIF('Must Buy'!D3:D11,"Joyroom",'Must Buy'!L3:L11)+SUMIF('Test Buy'!D3:D9,"Joyroom",'Test Buy'!L3:L9) -> 92910 | C16: =B16/C6 -> 0.78981596
A17: Anker | B17: =SUMIF('Must Buy'!D3:D11,"Anker",'Must Buy'!L3:L11)+SUMIF('Test Buy'!D3:D9,"Anker",'Test Buy'!L3:L9) -> 24725 | C17: =B17/C6 -> 0.21018404

Sheet Pricing Corrections
A1: Pricing Corrections Log — plan figures vs. the two source price lists
A2: SKU | B2: Product | C2: Plan says | D2: Source list says | E2: What this changes
A3: Anker A8852 | B3: PowerLine III C-C cable | C3: RDP 280 / RRP 460 | D3: RDP 460 / RRP 577 (Anker sheet, cables section, quoted twice) | E3: Margin drops from a claimed 39% to a real 20.3% — falls below this plan's own 35% 'Must Buy' bar. Recommend re-checking the real EG street price before ordering 20 units.
A4: Anker A2667 | B4: 735 PowerPort III, 3-Port 65W GaN charger | C4: RDP 830 / RRP 1,665 | D4: RDP 1,665 / RRP 1,995 (Anker sheet, chargers section, quoted twice) | E4: Margin drops from a claimed 50% to a real 16.5% — below this plan's own 20% 'Avoid' cut-off. The plan's assumed market range (1,000-1,400 ج.م) is also BELOW the real wholesale cost. Recommend moving this SKU from Test Buy to Avoid, or confirming a resale price above 1,665 ج.م first.
A5: Anker A1336 | B5: Prime Power Bank, 20,000mAh / 200W | C5: RDP 5,450 | D5: RDP 8,100 / RRP 9,898 (Anker sheet, power banks section) — 5,450 belongs to several unrelated MagGo wireless-charging docks (B2557 / B25M3 / B25M1) that happen to share that RDP | E5: Already correctly placed in Avoid; real margin is ~18%, not the ~28% quoted, so the case for avoiding it is actually stronger than stated.
A6: Joyroom JR-PK1 → JR-PR1 | B6: 22.5W retractable-cable power bank, 10,000mAh | C6: Model code 'JR-PK1' | D6: No 'JR-PK1' exists in the Joyroom list. Price quoted (990/1,399) matches model JR-PR1 exactly. | E6: Use JR-PR1 on the purchase order and in the free-sample ask to Joyroom — 'JR-PK1' will not be recognised.
A7: Joyroom SA21-1T3 | B7: 3-in-1 Speedy fast-charging cable | C7: RDP 265 / RRP 525 | D7: Joyroom lists TWO different products under SA21-1T3: a 30W Type-C-input version (RDP 275/RRP 550) and a 100W USB-A-input version (RDP 265/RRP 525). | E7: Plan's numbers match the 100W/USB-A version — make sure that is the one ordered, since the model code alone is ambiguous in Joyroom's own list.
A8: Joyroom JR-ZS259 | B8: Car phone holder | C8: RDP 225-270 / RRP 450-475 | D8: Joyroom lists TWO different holders under the same code JR-ZS259: a 'Holder with Flexible Arm for Dashboard' (RDP 270/RRP 475) and a clamp-style 'Dashboard' mount (RDP 225/RRP 450). | E8: The plan's range happens to cover both correctly, but the exact SKU should be confirmed with Joyroom before ordering — it is a live data-quality issue in their own list, not just this plan.

Sheet Additional Opportunities
A1: Additional Opportunities — priced in the supplier lists, not covered by the plan at all
A2: The procurement plan only reasons about cables/chargers/power banks/TWS. Both supplier lists carry whole categories with real RDP/RRP already quoted that never appear in the plan. Margin uses the same (RRP-RDP)/RRP basis as the rest of this workbook.
A3: # | B3: Category | C3: Example SKU | D3: Supplier | E3: RDP (EGP) | F3: RRP (EGP) | G3: Margin | H3: Note
A4: 1 | B4: eufy robot vacuums | C4: Robovac G50 Hybrid (T2212) | D4: eufy | E4: 13850 | F4: 16999 | G4: =(F4-E4)/F4 -> 0.18524619 | H4: 'Quiet cleaning' angle already in Anker's own marketing page — easy bundle with home/office setup solutions.
A5: 2 | B5: eufy trackers | C5: SmartTrack Card, Android (T87B5011) | D5: eufy | E5: 1380 | F5: 1666 | G5: =(F5-E5)/F5 -> 0.17166867 | H5: Small-ticket, high-margin, complements phone-case accessories.
A6: 3 | B6: Soundcore TWS earbuds | C6: R50i NC (A3959, ANC) | D6: Anker/Soundcore | E6: 1390 | F6: 1699 | G6: =(F6-E6)/F6 -> 0.18187169 | H6: Direct competitor to Joyroom JR-T03S at a higher price point — good up-sell pairing.
A7: 4 | B7: Soundcore headphones | C7: Q20i ANC over-ear (A3004) | D7: Anker/Soundcore | E7: 1850 | F7: 2100 | G7: =(F7-E7)/F7 -> 0.11904762 | H7: Only 13.5% margin at list RRP — reprice or negotiate before stocking.
A8: 5 | B8: Soundcore speakers | C8: Glow Mini (A3136) | D8: Anker/Soundcore | E8: 2799 | F8: 3350 | G8: =(F8-E8)/F8 -> 0.16447761 | H8: 16.5% margin at list RRP — check local market before committing quantity.
A9: 6 | B9: USB-C hubs / docks | C9: 332 USB-C Hub 5-in-1 (A8355) | D9: Anker | E9: 2220 | F9: 2788 | G9: =(F9-E9)/F9 -> 0.20373027 | H9: Laptop-accessory cross-sell for any 'ترقية اللابتوب' (laptop upgrade) solution ByteHub builds.
A10: 7 | B10: iPhone MagSafe cases | C10: iPhone 16 Pro Max Magnetic Case (A90H2) | D10: Anker (eufy line) | E10: 770 | F10: 939 | G10: =(F10-E10)/F10 -> 0.1799787 | H10: Pairs naturally with the screen-protector SKUs already in Must/Test Buy.
A11: 8 | B11: Joyroom smartwatches | C11: JR-FC3 Classic AMOLED (Answer/Make Call) | D11: Joyroom | E11: 2200 | F11: 2900 | G11: =(F11-E11)/F11 -> 0.24137931 | H11: New-product flag in Joyroom's own sheet — untested category for ByteHub.
A12: 9 | B12: Joyroom wireless charger | C12: Qi2 4-in-1 desk charger (JR-W23) | D12: Joyroom | E12: 1550 | F12: 1900 | G12: =(F12-E12)/F12 -> 0.18421053 | H12: 18.4% margin at list RRP — desk/home accessory, good with power-bank basket.
A13: 10 | B13: Joyroom hybrid ANC headphones | C13: JR-JH1 | D13: Joyroom | E13: 1300 | F13: 1950 | G13: =(F13-E13)/F13 -> 0.33333333 | H13: 33.3% margin — was named in the plan's own 'free sample' ask to Joyroom but never priced or added to a buy list.
A14: 11 | B14: Joyroom wired earphones | C14: Type-C EC05 half in-ear (JR-EC05) | D14: Joyroom | E14: 175 | F14: 410 | G14: =(F14-E14)/F14 -> 0.57317073 | H14: 57.3% margin — cheapest possible earphone SKU, good impulse/upsell item at checkout.
A15: 12 | B15: Joyroom stylus pen | C15: 3-in-1 Magnetic Capacitive Pen (JR-BP561) | D15: Joyroom | E15: 225 | F15: 550 | G15: =(F15-E15)/F15 -> 0.59090909 | H15: 59% margin — tablet-accessory cross-sell.

Sheet Website Readiness
A1: Website Readiness — 7 draft products from catalog_readiness.xlsx, matched to real supplier data
A2: catalog_readiness.xlsx also lists 3 draft/coming-soon Solutions and 6 coming-soon Services, and 22 build-blockers overall. The products below are the ones this catalogue can actually help close.
A3: # | B3: Draft product | C3: Key missing fields | D3: Recommended fix using this catalogue | E3: Real SKU / RDP-RRP if matched
A4: 1 | B4: Anker Soundcore R50i (ERBD-ANKR-R50I) | C4: price.amount, warranty_months, images, condition, compatible_with, specs.battery_life, specs.water_resistance | D4: Matches Anker's plain 'R50i VI' (no ANC/NC) in the Soundcore TWS section: 10mm driver, 10-30h battery in case, BT5.3, IPX5, 2-mic. Use this to fill battery_life and water_resistance directly; condition = New. | E4: A3969 · RDP 880 / RRP 1,099
A5: 2 | B5: Anker Soundcore R50i NC (ERBD-ANKR-R50INC) | C5: price.amount, warranty_months, images, condition, compatible_with, specs.battery_life, specs.water_resistance | D5: Matches Anker's 'R50i NC' (active noise cancelling): 10mm driver, 10-45h in case, BT5.4, IP54, 4-mic. | E5: A3959 · RDP 1,390 / RRP 1,699
A6: 3 | B6: قرص SSD بمنفذ SATA (مسودة) | C6: price, brand, capacity, warranty, stock_state, images, slug, why_we_chose_it, suited_for, read/write speed | D6: Product_Catalog (2) lists 5 SATA SSD candidates (Crucial BX500, Kingston A400, Lexar NS, PNY CS900, WD Blue SA510) with specs and 3-5yr warranties — but prices are USD estimates, not EG wholesale quotes. Use for the spec/description fields only; get a real EGP cost from a local distributor before setting price.amount. | E6: No verified EGP source yet
A7: 4 | B7: قرص SSD NVMe بمنفذ M.2 (مسودة) | C7: price, brand, capacity, warranty, stock_state, images, slug, why_we_chose_it, suited_for, read/write speed | D7: No NVMe/M.2 product exists anywhere across all 5 files supplied (Product_Catalog 1 & 2 are SATA/flash/RAM only). This is a genuine sourcing gap, not a data-entry gap — needs a new supplier quote from scratch. | E7: No source at all
A8: 5 | B8: ذاكرة RAM (مسودة) | C8: price, brand, capacity, ram_type, warranty, stock_state, images, slug, condition, why_we_chose_it, suited_for, speed, voltage | D8: Product_Catalog (1) lists 4 RAM SKUs (4GB DDR3L 1600 laptop, 4GB DDR4 2666 desktop, 4GB DDR3 1600 desktop, 8GB DDR3L 1600 desktop), all condition 'Original Used' — fills ram_type/speed/voltage/condition directly, but again needs an EGP cost before publishing. | E8: USD $5-15 est., unverified EGP
A9: 6 | B9: باور بانك (مسودة) | C9: price, brand, capacity, output_power, warranty, stock_state, images, slug, condition, why_we_chose_it, suited_for, compatible_with, ports | D9: Strongest match of all seven: Joyroom already has 8 fully-priced power banks in EGP, incl. two already approved as Must Buy (JR-PBF12, JR-QP192 Mini). Recommend retiring this generic draft and linking the listing straight to an approved Joyroom SKU instead of filling 13 fields by hand. | E9: e.g. JR-PBF12 · RDP 420 / RRP 730
A10: 7 | B10: شاحن جداري Joyroom (مسودة) | C10: price, output_power, warranty, stock_state, images, slug, condition, why_we_chose_it, suited_for, compatible_with, ports | D10: Same situation: Joyroom has 5+ wall chargers already priced, two already Must Buy (JR-TCG13, JR-TCF20). Retire the generic draft and link directly to the approved SKU rather than treating it as a separate product. | E10: e.g. JR-TCG13 · RDP 440 / RRP 750
A12: Other build blockers (not product data)
A13: • | B13: 2 products (R50i, R50i NC) still carry TODO placeholder copy for 'why_we_chose_it' and 'suited_for' — needs real marketing copy approved, not just a price fix.
A14: • | B14: Solution 'ترقية اللابتوب' (laptop upgrade) is status: draft and references the SSD/RAM/step products above — it cannot go live until those product gaps are closed, so treat this as the same blocker, not a separate one.
A15: • | B15: 3 Services (SSD+RAM install, data transfer, PC maintenance, networking, CCTV, digital services) are all still coming_soon and missing price_min/price_max/sla_hours — none of that pricing exists in any file supplied here; it needs to be set independently of the product catalogue.

Sheet Generic Catalog (USD)
A1: Generic Catalog (Product_Catalog 1 & 2) — NOT from Anker or Joyroom, in USD
A2: These 28 items (21 in Product_Catalog 1, 7 in Product_Catalog 2) are unrelated brands (Crucial, Kingston, Lexar, PNY, WD, Dell, HP, Logitech, Havit, AirLive, generic RAM) with estimated USD price ranges — not sourced from the Anker or Joyroom wholesale lists, and not currency-matched to the rest of this workbook. RECOMMENDATION: they map cleanly onto the 'laptop/PC upgrade' Solution and 'SSD+RAM install' Service already drafted in catalog_readiness.xlsx (see Website Readiness sheet) — keep them for THAT purpose, get a real EG distributor quote in EGP before publishing any price, and drop the categories with no ByteHub use case today (mouse pads, generic wired mice/keyboards) unless there's a reason to carry them.
A3: # | B3: Product | C3: Brand | D3: Category | E3: Est. Price (USD) | F3: Recommendation
A4: 1 | B4: Soundcore R50i TWS Earbuds | C4: Soundcore/Anker | D4: Earbuds | E4: $25-35 | F4: DUPLICATE — same product already exists as a real Anker SKU (A3969, RDP 880/RRP 1,099 EGP) on the Website Readiness sheet. Delete this generic USD entry; use the real one.
A5: 2 | B5: Soundcore P20i TWS Earbuds | C5: Soundcore/Anker | D5: Earbuds | E5: $20-28 | F5: Not found in the current Anker price list (17-Mar-2026) — either discontinued or needs a fresh RDP quote.
A6: 3 | B6: Soundcore Liberty 5 ANC Earbuds | C6: Soundcore/Anker | D6: Earbuds (Premium) | E6: $79-99 | F6: Real match exists: Anker 'Liberty 5' A3957, RDP 4,350 / RRP 5,111 EGP — replace the USD estimate with this.
A7: 4 | B7: Joyroom S-H153 USB-OTG Adapter | C7: Joyroom | D7: Adapters | E7: $3-7 | F7: Close relative exists in the Joyroom list (S-H152 USB-to-Type-C adapter, RDP 100/RRP 310 EGP) — confirm if S-H153 is a different SKU or a naming variant, then reprice in EGP.
A8: 5 | B8: Kingston / Hikvision / Lexar / SanDisk USB flash drives (4 SKUs) | C8: Mixed | D8: USB Flash Drives | E8: $4-20 | F8: No equivalent in Anker or Joyroom — genuinely new sourcing needed if ByteHub wants this category.
A9: 6 | B9: Dell / HP wired keyboards (2 SKUs) | C9: Dell / HP | D9: Keyboards | E9: $5-14 | F9: 'Original Used' condition, no supplier link — low priority unless refurb/PC-upgrade line is a real focus.
A10: 7 | B10: Wired mice — generic, Logitech B100 (2 SKUs) | C10: Dell/HP/Lenovo/Logitech | D10: Mice | E10: $3-12 | F10: Same as above — low priority, no current supplier.
A11: 8 | B11: Gaming mouse pads (2 SKUs) | C11: Havit / Wild Wolf | D11: Mouse Pads | E11: $3-8 | F11: No clear tie to ByteHub's current Joyroom/Anker mobile-accessories focus — candidate to drop.
A12: 9 | B12: Anker Zolo / Joyroom Mini Star power banks (2 SKUs) | C12: Anker / Joyroom | D12: Power Banks | E12: $22-40 | F12: DUPLICATE — real SKUs already covered: Anker A110D (already in Avoid) and Joyroom JR-QP191 Mini (RDP 675/RRP 999 EGP, close cousin of the approved JR-QP192 Mini). Delete generic entries, use real ones.
A13: 10 | B13: RAM — laptop/desktop DDR3/DDR3L/DDR4 (4 SKUs) | C13: Micron/Samsung/SK Hynix | D13: RAM | E13: $5-15 | F13: Keep for the 'ذاكرة RAM' draft product on Website Readiness — needs an EGP quote before publishing.
A14: 11 | B14: Crucial / Kingston / Lexar / PNY / WD SATA SSDs (5 SKUs) | C14: Mixed | D14: Internal SSD | E14: $20-60 | F14: Keep for the 'قرص SSD SATA' draft product on Website Readiness — needs an EGP quote before publishing.
A15: 12 | B15: AirLive USB Wi-Fi adapters (2 SKUs) | C15: AirLive | D15: Wi-Fi Adapters | E15: $6-15 | F15: No tie to current product lines or drafts — candidate to drop unless a networking-accessories push is planned.

Sheet Negotiation & KPIs
A1: Negotiation Playbook & Success KPIs (condensed from the plan, unchanged)
A3: Joyroom
A4: Ask | B4: Target | C4: Talking point
A5: Volume discount | B5: 5-10% off orders > 10,000 ج.م | C5: "We're planning a 30-40k initial order plus recurring monthly orders — what's your best price at that volume?"
A6: Free samples | B6: 2-3 units of JR-FN3, JR-PR1, JR-JH1 | C6: "We'd like to test 2-3 samples of new products before listing them — can these come free with the first order?"
A7: Payment terms | B7: Net 15-30 days | C7: "As a regular partner, can we agree to 15-day payment terms after delivery?"
A8: Marketing support | B8: Photos, videos, product copy | C8: "We're planning to actively market Joyroom in the Egyptian market — can you provide high-quality marketing assets?"
A9: Supply priority | B9: First access to new/high-demand SKUs | C9: "We'd like priority access to new and high-demand products, especially heading into peak seasons."
A11: Anker
A12: Ask | B12: Target | C12: Talking point
A13: Power-bank discount | B13: 25-30% off (up from 18-22%) | C13: "Current power-bank pricing doesn't compete with other suppliers — improve the discount to 25% and we'll commit to larger, recurring orders."
A14: Lightning-cable repricing | B14: A8843 to 1,500-1,700 ج.م, or drop it | C14: "A8843 doesn't fit the Egyptian market — competitors sell similar products at half the price. Can pricing be reviewed?"
A15: Bundles | B15: Charger + cable bundle pricing | C15: "We'd like bundled charger + cable pricing to help drive larger order sizes."
A16: Warranty support | B16: 14-day fast replacement | C16: "We're building our reputation on trust — please support fast replacement of defective units within 14 days."
A17: Quarterly review | B17: QBR on volume, pricing, new products | C17: "We'd like a quarterly meeting to review sales volume, pricing, and upcoming season planning."
A19: Success KPIs
A20: KPI | B20: Target | C20: How to measure
A21: Inventory turnover | B21: 2-3x / month | C21: Units sold ÷ average inventory
A22: Stagnant stock | B22: < 10% | C22: Products unsold after 30 days
A23: Gross margin | B23: > 35% | C23: (Revenue - COGS) ÷ Revenue
A24: Order fulfilment time | B24: < 48 hours | C24: Order received → delivered
A25: Customer satisfaction | B25: > 4.5 / 5 | C25: Customer ratings
A27: Note: the plan flags that all pricing should be re-checked monthly given FX volatility and supplier changes — the Anker sheet used here is dated 17-Mar-2026 and the Joyroom sheet 26-Jul-2026, so they are already ~4.5 months apart. Re-verify both before finalising any order.
